limited_numbers
